llm_client/__init__.py
llm_client/demo_tool_call_api.py
llm_client/example_full_usage.py
llm_client/factory.py
llm_client/interfaces.py
llm_client/llm_exceptions.py
llm_client/llm_utils.py
llm_client/models.py
llm_client/openai_client.py
llm_client/openai_provider.py
llm_client/paths.py
llm_client/response.py
forgebase/__init__.py
forgebase/commandbase.py
forgebase/controllerbase.py
forgebase/exceptionbase.py
forgebase/factories.py
forgebase/interfaces.py
forgebase/json_persistence.py
forgebase/modelbase.py
forgebase/persistencebase.py
forgebase/viewbase.py
forge_utils/__init__.py
forge_utils/log_service.py
forge_utils/paths.py
forgebase-0.2.12.dist-info/LICENSE
forgebase-0.2.12.dist-info/METADATA
forgebase-0.2.12.dist-info/WHEEL
forgebase-0.2.12.dist-info/RECORD
