Metadata-Version: 2.1
Name: forgebase
Version: 0.2.12
Summary: Forgebase core libraries (utils, framework e cliente LLM)
Home-page: https://github.com/palhanobrazil/forgebase
License: LGPL
Keywords: forgebase,framework,llm,openai
Author: palhano
Author-email: palhanobrazil@gmail.com
Requires-Python: >=3.11,<4.0
Classifier: License :: Other/Proprietary License
Classifier: Programming Language :: Python :: 3
Classifier: Programming Language :: Python :: 3.11
Classifier: Programming Language :: Python :: 3.12
Classifier: Topic :: Software Development :: Libraries
Classifier: Topic :: Software Development :: Libraries :: Application Frameworks
Requires-Dist: appdirs (>=1.4.4,<2.0.0)
Requires-Dist: backoff (>=2.2.1)
Requires-Dist: httpx (>=0.24.0)
Requires-Dist: pydantic (>=2.5)
Requires-Dist: python-dotenv (>=1.0.0)
Project-URL: Repository, https://github.com/palhanobrazil/forgebase
